msimilarities/__init__.py
msimilarities/bert_similarity.py
msimilarities/ensemble_similarity.py
msimilarities/fast_bert_similarity.py
msimilarities/literal_similarity.py
msimilarities/similarity.py
msimilarities/utils/__init__.py
msimilarities/utils/distance.py
msimilarities/utils/rank_bm25.py
msimilarities/utils/tfidf.py
msimilarities/utils/util.py
msimilarities-0.0.2.dist-info/LICENSE
msimilarities-0.0.2.dist-info/METADATA
msimilarities-0.0.2.dist-info/WHEEL
msimilarities-0.0.2.dist-info/top_level.txt
msimilarities-0.0.2.dist-info/RECORD
